cgd/__init__.py
cgd/__main__.py
cgd/cli_main.py
cgd/compile.py
cgd/constants.py
cgd/data.py
cgd/diff.py
cgd/execute.py
cgd/generate.py
cgd/log.py
cgd/template.py
cgd/utils.py
cgd/fc/__init__.py
cgd/fc/fc.py
cgd/fc/int_fc.py
cgd/fc/line_fc.py
cgd-0.0.2.dist-info/METADATA
cgd-0.0.2.dist-info/WHEEL
cgd-0.0.2.dist-info/entry_points.txt
cgd-0.0.2.dist-info/top_level.txt
cgd-0.0.2.dist-info/RECORD
