Metadata-Version: 2.1
Name: cgd
Version: 0.0.2
Summary: A auxiliary tool for algorithm competition questioner.
Home-page: https://github.com/malanore-z/CGD
Author: malanore.z
Author-email: malanore.z@gmail.com
Project-URL: Bug Tracker, https://github.com/malanore-z/CGD/issues
Classifier: Intended Audience :: Developers
Classifier: Programming Language :: Python :: 3
Classifier: License :: OSI Approved :: MIT License
Classifier: Operating System :: OS Independent
Requires-Python: >=3.6
Requires-Dist: zcommons
